amen/__init__.py
amen/auth.py
amen/cli.py
amen/editor.py
amen/frameworks.py
amen/monitor_web.py
amen/web.py
amen/static/fallback-bg.png
amen/static/tailwind.css
amen/static/tailwind.js
amen/static/tailwind.min.js
amen/templates/__init__.py
amen/templates/creator.html
amen/templates/manager.py
amen/templates/monitor.html
amen_cli-0.9.0.dist-info/METADATA
amen_cli-0.9.0.dist-info/WHEEL
amen_cli-0.9.0.dist-info/entry_points.txt
amen_cli-0.9.0.dist-info/licenses/LICENSE
amen_cli-0.9.0.dist-info/RECORD
