Metadata-Version: 2.4
Name: amen-cli
Version: 0.9.0
Summary: A laravel installer inspired Python Web Application Scaffolding Tool
Project-URL: Homepage, https://github.com/taqsblaze/amen-cli
Project-URL: Documentation, https://github.com/taqsblaze/amen-cli#readme
Project-URL: Repository, https://github.com/taqsblaze/amen-cli.git
Project-URL: Bug Tracker, https://github.com/taqsblaze/amen-cli/issues
Author-email: Tanaka Chinengundu <tanakah30@gmail.com>
License: Modified MIT License with Attribution Requirements
License-File: LICENSE
Classifier: Development Status :: 3 - Alpha
Classifier: Intended Audience :: Developers
Classifier: License :: OSI Approved :: MIT License
Classifier: Operating System :: OS Independent
Classifier: Programming Language :: Python :: 3
Classifier: Programming Language :: Python :: 3.11
Classifier: Topic :: Software Development :: Libraries :: Python Modules
Requires-Python: >=3.11
Requires-Dist: bandit>=1.7.0
Requires-Dist: click>=8.0.0
Requires-Dist: colorama>=0.4.4
Requires-Dist: pathlib>=1.0.0
Requires-Dist: psutil>=5.6.0
Requires-Dist: questionary>=1.10.0
Requires-Dist: requests>=2.25.0
Requires-Dist: rich>=0.1.0
Requires-Dist: rich>=12.0.0
Requires-Dist: tabulate>=0.8.9
Requires-Dist: virtualenv>=20.0.0
Provides-Extra: dev
Requires-Dist: black>=21.0.0; extra == 'dev'
Requires-Dist: flake8>=3.9.0; extra == 'dev'
Requires-Dist: mypy>=0.900; extra == 'dev'
Requires-Dist: pytest-cov>=2.0.0; extra == 'dev'
Requires-Dist: pytest>=6.0.0; extra == 'dev'
